pureai/RagPUREAI.cpython-312-x86_64-linux-gnu.so
pureai/__init__.py
pureai/libtorch_config.py
pureai-0.0.13.dist-info/METADATA
pureai-0.0.13.dist-info/WHEEL
pureai-0.0.13.dist-info/top_level.txt
pureai-0.0.13.dist-info/RECORD
